lic_cli/__init__.py
lic_cli/cli.py
lic_cli-0.1.11.dist-info/WHEEL
lic_cli-0.1.11.dist-info/entry_points.txt
lic_cli-0.1.11.dist-info/METADATA
lic_cli-0.1.11.dist-info/RECORD
