Metadata-Version: 2.3
Name: lic-cli
Version: 0.1.11
Summary: Minimal license generator
Author: kushvinth
Author-email: kushvinth <kushvinth.m@gmail.com>
Requires-Dist: rich>=13.0.0
Requires-Dist: httpx>=0.24.0
Requires-Dist: questionary>=2.0.0
Requires-Python: >=3.12
Project-URL: Homepage, https://github.com/kushvinth/lic
Project-URL: Issues, https://github.com/kushvinth/lic/issues
Project-URL: Repository, https://github.com/kushvinth/lic
